cloudinary_helper/__init__.py
cloudinary_helper/apps.py
cloudinary_helper/storages.py
cloudinary_helper/utils.py
tests/__init__.py
tests/test_storages.py
django_cloudinary_helper-0.3.7.dist-info/LICENSE
django_cloudinary_helper-0.3.7.dist-info/METADATA
django_cloudinary_helper-0.3.7.dist-info/WHEEL
django_cloudinary_helper-0.3.7.dist-info/top_level.txt
django_cloudinary_helper-0.3.7.dist-info/RECORD
