Metadata-Version: 2.1
Name: django-cloudinary-helper
Version: 0.3.7
Summary: Helper package for integrating Cloudinary with Django projects.
Home-page: https://github.com/snipher-marube/django-cloudinary-helper
Author: Snipher Marube
Author-email: sniphermarube@gmail.com
Classifier: Programming Language :: Python :: 3
Classifier: Framework :: Django
Classifier: License :: OSI Approved :: MIT License
Classifier: Operating System :: OS Independent
Requires-Python: >=3.7
License-File: LICENSE
Requires-Dist: django>=3.0
Requires-Dist: django-storages
Requires-Dist: cloudinary
Requires-Dist: python-decouple
Requires-Dist: pillow
